co2_cli_template/ const.py
co2_cli_template/__init__.py
co2_cli_template/cli/cli.py
co2_cli_template-0.1.0.dist-info/METADATA
co2_cli_template-0.1.0.dist-info/WHEEL
co2_cli_template-0.1.0.dist-info/RECORD
